fullstory_api/__init__.py
fullstory_api/fullstory_api.py
fullstory_api-0.1.3.dist-info/LICENSE
fullstory_api-0.1.3.dist-info/METADATA
fullstory_api-0.1.3.dist-info/WHEEL
fullstory_api-0.1.3.dist-info/top_level.txt
fullstory_api-0.1.3.dist-info/RECORD
